nightly/__init__.py
nightly-0.0.1.data/scripts/nightly
nightly-0.0.1.dist-info/METADATA
nightly-0.0.1.dist-info/WHEEL
nightly-0.0.1.dist-info/top_level.txt
nightly-0.0.1.dist-info/RECORD
