Metadata-Version: 2.1
Name: nightly
Version: 0.0.1
Summary: Nightly is a simple utility for executing a command every evening.
Home-page: https://github.com/johnjones4/nightly
Author: John E. Jones IV
Author-email: johnj@casefoundation.org
License: UNKNOWN
Platform: UNKNOWN
Classifier: Programming Language :: Python :: 3
Classifier: License :: OSI Approved :: MIT License
Classifier: Operating System :: OS Independent
